mwtext/__init__.py
mwtext/about.py
mwtext/mwtext.py
mwtext/content_transformers/__init__.py
mwtext/content_transformers/content_transformer.py
mwtext/content_transformers/util.py
mwtext/content_transformers/wikidata2words.py
mwtext/content_transformers/wikitext2structured.py
mwtext/content_transformers/wikitext2words.py
mwtext/filter_functions/__init__.py
mwtext/filter_functions/all_pages_and_revisions.py
mwtext/filter_functions/wikidata_items_with_wikipedia_sitelinks.py
mwtext/utilities/__init__.py
mwtext/utilities/learn_vectors.py
mwtext/utilities/transform_content.py
mwtext/utilities/util.py
mwtext/utilities/word2vec2gensim.py
mwtext/utilities/words2plaintext.py
tests/__init__.py
tests/content_transformers/__init__.py
tests/content_transformers/test_wikidata2words.py
tests/content_transformers/test_wikitext2structured.py
tests/content_transformers/test_wikitext2words.py
tests/content_transformers/wikilink_fixtures.py
mwtext-0.2.1.dist-info/LICENSE
mwtext-0.2.1.dist-info/METADATA
mwtext-0.2.1.dist-info/WHEEL
mwtext-0.2.1.dist-info/entry_points.txt
mwtext-0.2.1.dist-info/top_level.txt
mwtext-0.2.1.dist-info/RECORD
